{
	"info": {
		"_postman_id": "2587562e-db7a-481c-8a74-44f215fabb47",
		"name": "RestFull_Booker",
		"schema": "https://schema.getpostman.com/json/collection/v2.1.0/collection.json",
		"_exporter_id": "42570994",
		"_collection_link": "https://www.postman.com/flight-cosmologist-47429560/workspace/atb10x/collection/42570994-2587562e-db7a-481c-8a74-44f215fabb47?action=share&source=collection_link&creator=42570994"
	},
	"item": [
		{
			"name": "Get booking Ids",
			"request": {
				"method": "GET",
				"header": []
			},
			"response": []
		},
		{
			"name": "Get Booking",
			"request": {
				"method": "GET",
				"header": [],
				"url": {
					"raw": "https://restful-booker.herokuapp.com/booking/1",
					"protocol": "https",
					"host": [
						"restful-booker",
						"herokuapp",
						"com"
					],
					"path": [
						"booking",
						"1"
					]
				},
				"description": "Generated from cURL: curl -i https://restful-booker.herokuapp.com/booking/1"
			},
			"response": []
		},
		{
			"name": "CreateBooking positiveTC",
			"request": {
				"method": "POST",
				"header": [
					{
						"key": "Content-Type",
						"value": "application/json"
					}
				],
				"body": {
					"mode": "raw",
					"raw": "{\r\n    \"firstname\" : \"Jim\",\r\n    \"lastname\" : \"Brown\",\r\n    \"totalprice\" : 111,\r\n    \"depositpaid\" : true,\r\n    \"bookingdates\" : {\r\n        \"checkin\" : \"2018-01-01\",\r\n        \"checkout\" : \"2019-01-01\"\r\n    },\r\n    \"additionalneeds\" : \"Breakfast\"\r\n}",
					"options": {
						"raw": {
							"language": "json"
						}
					}
				},
				"url": {
					"raw": "https://restful-booker.herokuapp.com/booking",
					"protocol": "https",
					"host": [
						"restful-booker",
						"herokuapp",
						"com"
					],
					"path": [
						"booking"
					]
				},
				"description": "Generated from cURL: curl -X POST \\\r\n  https://restful-booker.herokuapp.com/booking \\\r\n  -H 'Content-Type: application/json' \\\r\n  -d '{\r\n    \"firstname\" : \"Jim\",\r\n    \"lastname\" : \"Brown\",\r\n    \"totalprice\" : 111,\r\n    \"depositpaid\" : true,\r\n    \"bookingdates\" : {\r\n        \"checkin\" : \"2018-01-01\",\r\n        \"checkout\" : \"2019-01-01\"\r\n    },\r\n    \"additionalneeds\" : \"Breakfast\"\r\n}'"
			},
			"response": []
		},
		{
			"name": "CreateBooking withouthearder",
			"request": {
				"method": "POST",
				"header": [
					{
						"key": "Content-Type",
						"value": "application/json",
						"disabled": true
					}
				],
				"body": {
					"mode": "raw",
					"raw": "{\r\n    \"firstname\" : \"Jim\",\r\n    \"lastname\" : \"Brown\",\r\n    \"totalprice\" : 111,\r\n    \"depositpaid\" : true,\r\n    \"bookingdates\" : {\r\n        \"checkin\" : \"2018-01-01\",\r\n        \"checkout\" : \"2019-01-01\"\r\n    },\r\n    \"additionalneeds\" : \"Breakfast\"\r\n}",
					"options": {
						"raw": {
							"language": "json"
						}
					}
				},
				"url": {
					"raw": "https://restful-booker.herokuapp.com/booking",
					"protocol": "https",
					"host": [
						"restful-booker",
						"herokuapp",
						"com"
					],
					"path": [
						"booking"
					]
				},
				"description": "Generated from cURL: curl -X POST \\\r\n  https://restful-booker.herokuapp.com/booking \\\r\n  -H 'Content-Type: application/json' \\\r\n  -d '{\r\n    \"firstname\" : \"Jim\",\r\n    \"lastname\" : \"Brown\",\r\n    \"totalprice\" : 111,\r\n    \"depositpaid\" : true,\r\n    \"bookingdates\" : {\r\n        \"checkin\" : \"2018-01-01\",\r\n        \"checkout\" : \"2019-01-01\"\r\n    },\r\n    \"additionalneeds\" : \"Breakfast\"\r\n}'"
			},
			"response": []
		},
		{
			"name": "CreateBooking_without additional_need",
			"request": {
				"method": "POST",
				"header": [
					{
						"key": "Content-Type",
						"value": "application/json"
					}
				],
				"body": {
					"mode": "raw",
					"raw": "{\r\n    \"firstname\" : \"Jim\",\r\n    \"lastname\" : \"Brown\",\r\n    \"totalprice\" : 111,\r\n    \"depositpaid\" : true,\r\n    \"bookingdates\" : {\r\n        \"checkin\" : \"2018-01-01\",\r\n        \"checkout\" : \"2019-01-01\"\r\n    },\r\n    \"additionalneeds\" : \"Breakfast\"\r\n}",
					"options": {
						"raw": {
							"language": "json"
						}
					}
				},
				"url": {
					"raw": "https://restful-booker.herokuapp.com/booking",
					"protocol": "https",
					"host": [
						"restful-booker",
						"herokuapp",
						"com"
					],
					"path": [
						"booking"
					]
				},
				"description": "Generated from cURL: curl -X POST \\\r\n  https://restful-booker.herokuapp.com/booking \\\r\n  -H 'Content-Type: application/json' \\\r\n  -d '{\r\n    \"firstname\" : \"Jim\",\r\n    \"lastname\" : \"Brown\",\r\n    \"totalprice\" : 111,\r\n    \"depositpaid\" : true,\r\n    \"bookingdates\" : {\r\n        \"checkin\" : \"2018-01-01\",\r\n        \"checkout\" : \"2019-01-01\"\r\n    },\r\n    \"additionalneeds\" : \"Breakfast\"\r\n}'"
			},
			"response": []
		},
		{
			"name": "CreateBooking_different_currency_format",
			"request": {
				"method": "POST",
				"header": [
					{
						"key": "Content-Type",
						"value": "application/json"
					}
				],
				"body": {
					"mode": "raw",
					"raw": "{\r\n    \"firstname\" : \"Jim\",\r\n    \"lastname\" : \"Brown\",\r\n    \"totalprice\" : 111,\r\n    \"depositpaid\" : true,\r\n    \"bookingdates\" : {\r\n        \"checkin\" : \"2018-01-01\",\r\n        \"checkout\" : \"2019-01-01\"\r\n    },\r\n    \"additionalneeds\" : \"Breakfast\"\r\n}",
					"options": {
						"raw": {
							"language": "json"
						}
					}
				},
				"url": {
					"raw": "https://restful-booker.herokuapp.com/booking",
					"protocol": "https",
					"host": [
						"restful-booker",
						"herokuapp",
						"com"
					],
					"path": [
						"booking"
					]
				},
				"description": "Generated from cURL: curl -X POST \\\r\n  https://restful-booker.herokuapp.com/booking \\\r\n  -H 'Content-Type: application/json' \\\r\n  -d '{\r\n    \"firstname\" : \"Jim\",\r\n    \"lastname\" : \"Brown\",\r\n    \"totalprice\" : 111,\r\n    \"depositpaid\" : true,\r\n    \"bookingdates\" : {\r\n        \"checkin\" : \"2018-01-01\",\r\n        \"checkout\" : \"2019-01-01\"\r\n    },\r\n    \"additionalneeds\" : \"Breakfast\"\r\n}'"
			},
			"response": []
		},
		{
			"name": "CreateBooking_depositpaid with false",
			"request": {
				"method": "POST",
				"header": [
					{
						"key": "Content-Type",
						"value": "application/json"
					}
				],
				"body": {
					"mode": "raw",
					"raw": "{\r\n    \"firstname\" : \"Jim\",\r\n    \"lastname\" : \"Brown\",\r\n    \"totalprice\" : 111,\r\n    \"depositpaid\" : true,\r\n    \"bookingdates\" : {\r\n        \"checkin\" : \"2018-01-01\",\r\n        \"checkout\" : \"2019-01-01\"\r\n    },\r\n    \"additionalneeds\" : \"Breakfast\"\r\n}",
					"options": {
						"raw": {
							"language": "json"
						}
					}
				},
				"url": {
					"raw": "https://restful-booker.herokuapp.com/booking",
					"protocol": "https",
					"host": [
						"restful-booker",
						"herokuapp",
						"com"
					],
					"path": [
						"booking"
					]
				},
				"description": "Generated from cURL: curl -X POST \\\r\n  https://restful-booker.herokuapp.com/booking \\\r\n  -H 'Content-Type: application/json' \\\r\n  -d '{\r\n    \"firstname\" : \"Jim\",\r\n    \"lastname\" : \"Brown\",\r\n    \"totalprice\" : 111,\r\n    \"depositpaid\" : true,\r\n    \"bookingdates\" : {\r\n        \"checkin\" : \"2018-01-01\",\r\n        \"checkout\" : \"2019-01-01\"\r\n    },\r\n    \"additionalneeds\" : \"Breakfast\"\r\n}'"
			},
			"response": []
		},
		{
			"name": "CreateBooking_future_date",
			"request": {
				"method": "POST",
				"header": [
					{
						"key": "Content-Type",
						"value": "application/json"
					}
				],
				"body": {
					"mode": "raw",
					"raw": "{\r\n    \"firstname\" : \"Jim\",\r\n    \"lastname\" : \"Brown\",\r\n    \"totalprice\" : 111,\r\n    \"depositpaid\" : true,\r\n    \"bookingdates\" : {\r\n        \"checkin\" : \"2018-01-01\",\r\n        \"checkout\" : \"2019-01-01\"\r\n    },\r\n    \"additionalneeds\" : \"Breakfast\"\r\n}",
					"options": {
						"raw": {
							"language": "json"
						}
					}
				},
				"url": {
					"raw": "https://restful-booker.herokuapp.com/booking",
					"protocol": "https",
					"host": [
						"restful-booker",
						"herokuapp",
						"com"
					],
					"path": [
						"booking"
					]
				},
				"description": "Generated from cURL: curl -X POST \\\r\n  https://restful-booker.herokuapp.com/booking \\\r\n  -H 'Content-Type: application/json' \\\r\n  -d '{\r\n    \"firstname\" : \"Jim\",\r\n    \"lastname\" : \"Brown\",\r\n    \"totalprice\" : 111,\r\n    \"depositpaid\" : true,\r\n    \"bookingdates\" : {\r\n        \"checkin\" : \"2018-01-01\",\r\n        \"checkout\" : \"2019-01-01\"\r\n    },\r\n    \"additionalneeds\" : \"Breakfast\"\r\n}'"
			},
			"response": []
		},
		{
			"name": "CreateBooking_with only mandatory fields",
			"request": {
				"method": "POST",
				"header": [
					{
						"key": "Content-Type",
						"value": "application/json"
					}
				],
				"body": {
					"mode": "raw",
					"raw": "{\r\n    \"firstname\" : \"Jim\",\r\n    \"lastname\" : \"Brown\",\r\n    \"totalprice\" : 111,\r\n    \"depositpaid\" : true,\r\n    \"bookingdates\" : {\r\n        \"checkin\" : \"2018-01-01\",\r\n        \"checkout\" : \"2019-01-01\"\r\n    },\r\n    \"additionalneeds\" : \"Breakfast\"\r\n}",
					"options": {
						"raw": {
							"language": "json"
						}
					}
				},
				"url": {
					"raw": "https://restful-booker.herokuapp.com/booking",
					"protocol": "https",
					"host": [
						"restful-booker",
						"herokuapp",
						"com"
					],
					"path": [
						"booking"
					]
				},
				"description": "Generated from cURL: curl -X POST \\\r\n  https://restful-booker.herokuapp.com/booking \\\r\n  -H 'Content-Type: application/json' \\\r\n  -d '{\r\n    \"firstname\" : \"Jim\",\r\n    \"lastname\" : \"Brown\",\r\n    \"totalprice\" : 111,\r\n    \"depositpaid\" : true,\r\n    \"bookingdates\" : {\r\n        \"checkin\" : \"2018-01-01\",\r\n        \"checkout\" : \"2019-01-01\"\r\n    },\r\n    \"additionalneeds\" : \"Breakfast\"\r\n}'"
			},
			"response": []
		},
		{
			"name": "CreateBooking_with_an_empty \"additionalneeds\" field",
			"request": {
				"method": "POST",
				"header": [
					{
						"key": "Content-Type",
						"value": "application/json"
					}
				],
				"body": {
					"mode": "raw",
					"raw": "{\r\n    \"firstname\" : \"Jim\",\r\n    \"lastname\" : \"Brown\",\r\n    \"totalprice\" : 111,\r\n    \"depositpaid\" : true,\r\n    \"bookingdates\" : {\r\n        \"checkin\" : \"2018-01-01\",\r\n        \"checkout\" : \"2019-01-01\"\r\n    },\r\n    \"additionalneeds\" : \"Breakfast\"\r\n}",
					"options": {
						"raw": {
							"language": "json"
						}
					}
				},
				"url": {
					"raw": "https://restful-booker.herokuapp.com/booking",
					"protocol": "https",
					"host": [
						"restful-booker",
						"herokuapp",
						"com"
					],
					"path": [
						"booking"
					]
				},
				"description": "Generated from cURL: curl -X POST \\\r\n  https://restful-booker.herokuapp.com/booking \\\r\n  -H 'Content-Type: application/json' \\\r\n  -d '{\r\n    \"firstname\" : \"Jim\",\r\n    \"lastname\" : \"Brown\",\r\n    \"totalprice\" : 111,\r\n    \"depositpaid\" : true,\r\n    \"bookingdates\" : {\r\n        \"checkin\" : \"2018-01-01\",\r\n        \"checkout\" : \"2019-01-01\"\r\n    },\r\n    \"additionalneeds\" : \"Breakfast\"\r\n}'"
			},
			"response": []
		},
		{
			"name": "CreateBooking_with large text values",
			"request": {
				"method": "POST",
				"header": [
					{
						"key": "Content-Type",
						"value": "application/json"
					}
				],
				"body": {
					"mode": "raw",
					"raw": "{\r\n    \"firstname\" : \"Jim\",\r\n    \"lastname\" : \"Brown\",\r\n    \"totalprice\" : 111,\r\n    \"depositpaid\" : true,\r\n    \"bookingdates\" : {\r\n        \"checkin\" : \"2018-01-01\",\r\n        \"checkout\" : \"2019-01-01\"\r\n    },\r\n    \"additionalneeds\" : \"Breakfast\"\r\n}",
					"options": {
						"raw": {
							"language": "json"
						}
					}
				},
				"url": {
					"raw": "https://restful-booker.herokuapp.com/booking",
					"protocol": "https",
					"host": [
						"restful-booker",
						"herokuapp",
						"com"
					],
					"path": [
						"booking"
					]
				},
				"description": "Generated from cURL: curl -X POST \\\r\n  https://restful-booker.herokuapp.com/booking \\\r\n  -H 'Content-Type: application/json' \\\r\n  -d '{\r\n    \"firstname\" : \"Jim\",\r\n    \"lastname\" : \"Brown\",\r\n    \"totalprice\" : 111,\r\n    \"depositpaid\" : true,\r\n    \"bookingdates\" : {\r\n        \"checkin\" : \"2018-01-01\",\r\n        \"checkout\" : \"2019-01-01\"\r\n    },\r\n    \"additionalneeds\" : \"Breakfast\"\r\n}'"
			},
			"response": []
		},
		{
			"name": "CreateBooking with special char",
			"request": {
				"method": "POST",
				"header": [
					{
						"key": "Content-Type",
						"value": "application/json"
					}
				],
				"body": {
					"mode": "raw",
					"raw": "{\r\n    \"firstname\" : \"Jim\",\r\n    \"lastname\" : \"Brown\",\r\n    \"totalprice\" : 111,\r\n    \"depositpaid\" : true,\r\n    \"bookingdates\" : {\r\n        \"checkin\" : \"2018-01-01\",\r\n        \"checkout\" : \"2019-01-01\"\r\n    },\r\n    \"additionalneeds\" : \"Breakfast\"\r\n}",
					"options": {
						"raw": {
							"language": "json"
						}
					}
				},
				"url": {
					"raw": "https://restful-booker.herokuapp.com/booking",
					"protocol": "https",
					"host": [
						"restful-booker",
						"herokuapp",
						"com"
					],
					"path": [
						"booking"
					]
				},
				"description": "Generated from cURL: curl -X POST \\\r\n  https://restful-booker.herokuapp.com/booking \\\r\n  -H 'Content-Type: application/json' \\\r\n  -d '{\r\n    \"firstname\" : \"Jim\",\r\n    \"lastname\" : \"Brown\",\r\n    \"totalprice\" : 111,\r\n    \"depositpaid\" : true,\r\n    \"bookingdates\" : {\r\n        \"checkin\" : \"2018-01-01\",\r\n        \"checkout\" : \"2019-01-01\"\r\n    },\r\n    \"additionalneeds\" : \"Breakfast\"\r\n}'"
			},
			"response": []
		},
		{
			"name": "CreateBooking RemoveFirstname",
			"request": {
				"method": "POST",
				"header": [
					{
						"key": "Content-Type",
						"value": "application/json"
					}
				],
				"body": {
					"mode": "raw",
					"raw": "{\r\n    \"firstname\" : \"Jim\",\r\n    \"lastname\" : \"Brown\",\r\n    \"totalprice\" : 111,\r\n    \"depositpaid\" : true,\r\n    \"bookingdates\" : {\r\n        \"checkin\" : \"2018-01-01\",\r\n        \"checkout\" : \"2019-01-01\"\r\n    },\r\n    \"additionalneeds\" : \"Breakfast\"\r\n}",
					"options": {
						"raw": {
							"language": "json"
						}
					}
				},
				"url": {
					"raw": "https://restful-booker.herokuapp.com/booking",
					"protocol": "https",
					"host": [
						"restful-booker",
						"herokuapp",
						"com"
					],
					"path": [
						"booking"
					]
				},
				"description": "Generated from cURL: curl -X POST \\\r\n  https://restful-booker.herokuapp.com/booking \\\r\n  -H 'Content-Type: application/json' \\\r\n  -d '{\r\n    \"firstname\" : \"Jim\",\r\n    \"lastname\" : \"Brown\",\r\n    \"totalprice\" : 111,\r\n    \"depositpaid\" : true,\r\n    \"bookingdates\" : {\r\n        \"checkin\" : \"2018-01-01\",\r\n        \"checkout\" : \"2019-01-01\"\r\n    },\r\n    \"additionalneeds\" : \"Breakfast\"\r\n}'"
			},
			"response": []
		},
		{
			"name": "CreateBooking_Missing lastname",
			"request": {
				"method": "POST",
				"header": [
					{
						"key": "Content-Type",
						"value": "application/json"
					}
				],
				"body": {
					"mode": "raw",
					"raw": "{\r\n    \"firstname\" : \"Jim\",\r\n    \"lastname\" : \"Brown\",\r\n    \"totalprice\" : 111,\r\n    \"depositpaid\" : true,\r\n    \"bookingdates\" : {\r\n        \"checkin\" : \"2018-01-01\",\r\n        \"checkout\" : \"2019-01-01\"\r\n    },\r\n    \"additionalneeds\" : \"Breakfast\"\r\n}",
					"options": {
						"raw": {
							"language": "json"
						}
					}
				},
				"url": {
					"raw": "https://restful-booker.herokuapp.com/booking",
					"protocol": "https",
					"host": [
						"restful-booker",
						"herokuapp",
						"com"
					],
					"path": [
						"booking"
					]
				},
				"description": "Generated from cURL: curl -X POST \\\r\n  https://restful-booker.herokuapp.com/booking \\\r\n  -H 'Content-Type: application/json' \\\r\n  -d '{\r\n    \"firstname\" : \"Jim\",\r\n    \"lastname\" : \"Brown\",\r\n    \"totalprice\" : 111,\r\n    \"depositpaid\" : true,\r\n    \"bookingdates\" : {\r\n        \"checkin\" : \"2018-01-01\",\r\n        \"checkout\" : \"2019-01-01\"\r\n    },\r\n    \"additionalneeds\" : \"Breakfast\"\r\n}'"
			},
			"response": []
		},
		{
			"name": "CreateBooking _Missingtotalprice",
			"request": {
				"method": "POST",
				"header": [
					{
						"key": "Content-Type",
						"value": "application/json"
					}
				],
				"body": {
					"mode": "raw",
					"raw": "{\r\n    \"firstname\" : \"Jim\",\r\n    \"lastname\" : \"Brown\",\r\n    \"totalprice\" : 111,\r\n    \"depositpaid\" : true,\r\n    \"bookingdates\" : {\r\n        \"checkin\" : \"2018-01-01\",\r\n        \"checkout\" : \"2019-01-01\"\r\n    },\r\n    \"additionalneeds\" : \"Breakfast\"\r\n}",
					"options": {
						"raw": {
							"language": "json"
						}
					}
				},
				"url": {
					"raw": "https://restful-booker.herokuapp.com/booking",
					"protocol": "https",
					"host": [
						"restful-booker",
						"herokuapp",
						"com"
					],
					"path": [
						"booking"
					]
				},
				"description": "Generated from cURL: curl -X POST \\\r\n  https://restful-booker.herokuapp.com/booking \\\r\n  -H 'Content-Type: application/json' \\\r\n  -d '{\r\n    \"firstname\" : \"Jim\",\r\n    \"lastname\" : \"Brown\",\r\n    \"totalprice\" : 111,\r\n    \"depositpaid\" : true,\r\n    \"bookingdates\" : {\r\n        \"checkin\" : \"2018-01-01\",\r\n        \"checkout\" : \"2019-01-01\"\r\n    },\r\n    \"additionalneeds\" : \"Breakfast\"\r\n}'"
			},
			"response": []
		},
		{
			"name": "CreateBooking _Missing bookingDates",
			"request": {
				"method": "POST",
				"header": [
					{
						"key": "Content-Type",
						"value": "application/json"
					}
				],
				"body": {
					"mode": "raw",
					"raw": "{\r\n    \"firstname\" : \"Jim\",\r\n    \"lastname\" : \"Brown\",\r\n    \"totalprice\" : 111,\r\n    \"depositpaid\" : true,\r\n    \"bookingdates\" : {\r\n        \"checkin\" : \"2018-01-01\",\r\n        \"checkout\" : \"2019-01-01\"\r\n    },\r\n    \"additionalneeds\" : \"Breakfast\"\r\n}",
					"options": {
						"raw": {
							"language": "json"
						}
					}
				},
				"url": {
					"raw": "https://restful-booker.herokuapp.com/booking",
					"protocol": "https",
					"host": [
						"restful-booker",
						"herokuapp",
						"com"
					],
					"path": [
						"booking"
					]
				},
				"description": "Generated from cURL: curl -X POST \\\r\n  https://restful-booker.herokuapp.com/booking \\\r\n  -H 'Content-Type: application/json' \\\r\n  -d '{\r\n    \"firstname\" : \"Jim\",\r\n    \"lastname\" : \"Brown\",\r\n    \"totalprice\" : 111,\r\n    \"depositpaid\" : true,\r\n    \"bookingdates\" : {\r\n        \"checkin\" : \"2018-01-01\",\r\n        \"checkout\" : \"2019-01-01\"\r\n    },\r\n    \"additionalneeds\" : \"Breakfast\"\r\n}'"
			},
			"response": []
		},
		{
			"name": "CreateBooking _ with check-out date before check-in date",
			"request": {
				"method": "POST",
				"header": [
					{
						"key": "Content-Type",
						"value": "application/json"
					}
				],
				"body": {
					"mode": "raw",
					"raw": "{\r\n    \"firstname\" : \"Jim\",\r\n    \"lastname\" : \"Brown\",\r\n    \"totalprice\" : 111,\r\n    \"depositpaid\" : true,\r\n    \"bookingdates\" : {\r\n        \"checkin\" : \"2018-01-01\",\r\n        \"checkout\" : \"2019-01-01\"\r\n    },\r\n    \"additionalneeds\" : \"Breakfast\"\r\n}",
					"options": {
						"raw": {
							"language": "json"
						}
					}
				},
				"url": {
					"raw": "https://restful-booker.herokuapp.com/booking",
					"protocol": "https",
					"host": [
						"restful-booker",
						"herokuapp",
						"com"
					],
					"path": [
						"booking"
					]
				},
				"description": "Generated from cURL: curl -X POST \\\r\n  https://restful-booker.herokuapp.com/booking \\\r\n  -H 'Content-Type: application/json' \\\r\n  -d '{\r\n    \"firstname\" : \"Jim\",\r\n    \"lastname\" : \"Brown\",\r\n    \"totalprice\" : 111,\r\n    \"depositpaid\" : true,\r\n    \"bookingdates\" : {\r\n        \"checkin\" : \"2018-01-01\",\r\n        \"checkout\" : \"2019-01-01\"\r\n    },\r\n    \"additionalneeds\" : \"Breakfast\"\r\n}'"
			},
			"response": []
		},
		{
			"name": "CreateBooking _with non-numeric \"totalprice\"",
			"request": {
				"method": "POST",
				"header": [
					{
						"key": "Content-Type",
						"value": "application/json"
					}
				],
				"body": {
					"mode": "raw",
					"raw": "{\r\n    \"firstname\" : \"Jim\",\r\n    \"lastname\" : \"Brown\",\r\n    \"totalprice\" : 111,\r\n    \"depositpaid\" : true,\r\n    \"bookingdates\" : {\r\n        \"checkin\" : \"2018-01-01\",\r\n        \"checkout\" : \"2019-01-01\"\r\n    },\r\n    \"additionalneeds\" : \"Breakfast\"\r\n}",
					"options": {
						"raw": {
							"language": "json"
						}
					}
				},
				"url": {
					"raw": "https://restful-booker.herokuapp.com/booking",
					"protocol": "https",
					"host": [
						"restful-booker",
						"herokuapp",
						"com"
					],
					"path": [
						"booking"
					]
				},
				"description": "Generated from cURL: curl -X POST \\\r\n  https://restful-booker.herokuapp.com/booking \\\r\n  -H 'Content-Type: application/json' \\\r\n  -d '{\r\n    \"firstname\" : \"Jim\",\r\n    \"lastname\" : \"Brown\",\r\n    \"totalprice\" : 111,\r\n    \"depositpaid\" : true,\r\n    \"bookingdates\" : {\r\n        \"checkin\" : \"2018-01-01\",\r\n        \"checkout\" : \"2019-01-01\"\r\n    },\r\n    \"additionalneeds\" : \"Breakfast\"\r\n}'"
			},
			"response": []
		},
		{
			"name": "CreateBooking_with an invalid date format",
			"request": {
				"method": "POST",
				"header": [
					{
						"key": "Content-Type",
						"value": "application/json"
					}
				],
				"body": {
					"mode": "raw",
					"raw": "{\r\n    \"firstname\" : \"Jim\",\r\n    \"lastname\" : \"Brown\",\r\n    \"totalprice\" : 111,\r\n    \"depositpaid\" : true,\r\n    \"bookingdates\" : {\r\n        \"checkin\" : \"2018-01-01\",\r\n        \"checkout\" : \"2019-01-01\"\r\n    },\r\n    \"additionalneeds\" : \"Breakfast\"\r\n}",
					"options": {
						"raw": {
							"language": "json"
						}
					}
				},
				"url": {
					"raw": "https://restful-booker.herokuapp.com/booking",
					"protocol": "https",
					"host": [
						"restful-booker",
						"herokuapp",
						"com"
					],
					"path": [
						"booking"
					]
				},
				"description": "Generated from cURL: curl -X POST \\\r\n  https://restful-booker.herokuapp.com/booking \\\r\n  -H 'Content-Type: application/json' \\\r\n  -d '{\r\n    \"firstname\" : \"Jim\",\r\n    \"lastname\" : \"Brown\",\r\n    \"totalprice\" : 111,\r\n    \"depositpaid\" : true,\r\n    \"bookingdates\" : {\r\n        \"checkin\" : \"2018-01-01\",\r\n        \"checkout\" : \"2019-01-01\"\r\n    },\r\n    \"additionalneeds\" : \"Breakfast\"\r\n}'"
			},
			"response": []
		},
		{
			"name": "CreateBooking _missing \"depositpaid\" field",
			"request": {
				"method": "POST",
				"header": [
					{
						"key": "Content-Type",
						"value": "application/json"
					}
				],
				"body": {
					"mode": "raw",
					"raw": "{\r\n    \"firstname\" : \"Jim\",\r\n    \"lastname\" : \"Brown\",\r\n    \"totalprice\" : 111,\r\n    \"depositpaid\" : true,\r\n    \"bookingdates\" : {\r\n        \"checkin\" : \"2018-01-01\",\r\n        \"checkout\" : \"2019-01-01\"\r\n    },\r\n    \"additionalneeds\" : \"Breakfast\"\r\n}",
					"options": {
						"raw": {
							"language": "json"
						}
					}
				},
				"url": {
					"raw": "https://restful-booker.herokuapp.com/booking",
					"protocol": "https",
					"host": [
						"restful-booker",
						"herokuapp",
						"com"
					],
					"path": [
						"booking"
					]
				},
				"description": "Generated from cURL: curl -X POST \\\r\n  https://restful-booker.herokuapp.com/booking \\\r\n  -H 'Content-Type: application/json' \\\r\n  -d '{\r\n    \"firstname\" : \"Jim\",\r\n    \"lastname\" : \"Brown\",\r\n    \"totalprice\" : 111,\r\n    \"depositpaid\" : true,\r\n    \"bookingdates\" : {\r\n        \"checkin\" : \"2018-01-01\",\r\n        \"checkout\" : \"2019-01-01\"\r\n    },\r\n    \"additionalneeds\" : \"Breakfast\"\r\n}'"
			},
			"response": []
		},
		{
			"name": "CreateBookingwith an empty request body",
			"request": {
				"method": "POST",
				"header": [
					{
						"key": "Content-Type",
						"value": "application/json"
					}
				],
				"body": {
					"mode": "raw",
					"raw": "{\r\n    \"firstname\" : \"Jim\",\r\n    \"lastname\" : \"Brown\",\r\n    \"totalprice\" : 111,\r\n    \"depositpaid\" : true,\r\n    \"bookingdates\" : {\r\n        \"checkin\" : \"2018-01-01\",\r\n        \"checkout\" : \"2019-01-01\"\r\n    },\r\n    \"additionalneeds\" : \"Breakfast\"\r\n}",
					"options": {
						"raw": {
							"language": "json"
						}
					}
				},
				"url": {
					"raw": "https://restful-booker.herokuapp.com/booking",
					"protocol": "https",
					"host": [
						"restful-booker",
						"herokuapp",
						"com"
					],
					"path": [
						"booking"
					]
				},
				"description": "Generated from cURL: curl -X POST \\\r\n  https://restful-booker.herokuapp.com/booking \\\r\n  -H 'Content-Type: application/json' \\\r\n  -d '{\r\n    \"firstname\" : \"Jim\",\r\n    \"lastname\" : \"Brown\",\r\n    \"totalprice\" : 111,\r\n    \"depositpaid\" : true,\r\n    \"bookingdates\" : {\r\n        \"checkin\" : \"2018-01-01\",\r\n        \"checkout\" : \"2019-01-01\"\r\n    },\r\n    \"additionalneeds\" : \"Breakfast\"\r\n}'"
			},
			"response": []
		},
		{
			"name": "CreateBooking_with an invalid endpoint",
			"request": {
				"method": "POST",
				"header": [
					{
						"key": "Content-Type",
						"value": "application/json"
					}
				],
				"body": {
					"mode": "raw",
					"raw": "{\r\n    \"firstname\" : \"Jim\",\r\n    \"lastname\" : \"Brown\",\r\n    \"totalprice\" : 111,\r\n    \"depositpaid\" : true,\r\n    \"bookingdates\" : {\r\n        \"checkin\" : \"2018-01-01\",\r\n        \"checkout\" : \"2019-01-01\"\r\n    },\r\n    \"additionalneeds\" : \"Breakfast\"\r\n}",
					"options": {
						"raw": {
							"language": "json"
						}
					}
				},
				"url": {
					"raw": "https://restful-booker.herokuapp.com/booking",
					"protocol": "https",
					"host": [
						"restful-booker",
						"herokuapp",
						"com"
					],
					"path": [
						"booking"
					]
				},
				"description": "Generated from cURL: curl -X POST \\\r\n  https://restful-booker.herokuapp.com/booking \\\r\n  -H 'Content-Type: application/json' \\\r\n  -d '{\r\n    \"firstname\" : \"Jim\",\r\n    \"lastname\" : \"Brown\",\r\n    \"totalprice\" : 111,\r\n    \"depositpaid\" : true,\r\n    \"bookingdates\" : {\r\n        \"checkin\" : \"2018-01-01\",\r\n        \"checkout\" : \"2019-01-01\"\r\n    },\r\n    \"additionalneeds\" : \"Breakfast\"\r\n}'"
			},
			"response": []
		}
	]
}